arrakis/__init__.py
arrakis/src/__init__.py
arrakis/src/bench/__init__.py
arrakis/src/bench/base_bench.py
arrakis/src/core_arrakis/__init__.py
arrakis/src/core_arrakis/activation_cache.py
arrakis/src/core_arrakis/attention_head_comp.py
arrakis/src/core_arrakis/attention_tools.py
arrakis/src/core_arrakis/base_interpret.py
arrakis/src/core_arrakis/causal_tracing_intervention.py
arrakis/src/core_arrakis/factored_matrix.py
arrakis/src/core_arrakis/feature_viz.py
arrakis/src/core_arrakis/kg_extractor.py
arrakis/src/core_arrakis/knowledge_prober.py
arrakis/src/core_arrakis/logit_attribution.py
arrakis/src/core_arrakis/logit_lens.py
arrakis/src/core_arrakis/model_surgery.py
arrakis/src/core_arrakis/read_write_heads.py
arrakis/src/core_arrakis/residual_decomposer.py
arrakis/src/core_arrakis/residual_tools.py
arrakis/src/core_arrakis/sparsity_analyzer.py
arrakis/src/core_arrakis/superposition_disentangler.py
arrakis/src/graph/__init__.py
arrakis/src/graph/base_graph.py
arrakis_mi-0.1.1.dist-info/METADATA
arrakis_mi-0.1.1.dist-info/WHEEL
arrakis_mi-0.1.1.dist-info/RECORD
