Metadata-Version: 2.1
Name: arrakis-mi
Version: 0.1.1
Summary: A mechanistic interpretability library for nerds.
Home-page: https://github.com/yash-srivastava19/arrakis
License: MIT
Author: Yash Srivastava
Author-email: ysrivastava82@gmail.com
Requires-Python: >=3.11,<4.0
Classifier: License :: OSI Approved :: MIT License
Classifier: Programming Language :: Python :: 3
Classifier: Programming Language :: Python :: 3.11
Classifier: Programming Language :: Python :: 3.12
Requires-Dist: numpy (<2)
Requires-Dist: seaborn (>=0.13.2,<0.14.0)
Requires-Dist: torch (==2.2.1)
Requires-Dist: transformers (>=4.41.2,<5.0.0)
Project-URL: Documentation, https://arrakis-mi.readthedocs.io/en/latest/README.html
Project-URL: Repository, https://github.com/yash-srivastava19/arrakis
